README.md
setup.cfg
setup.py
aiok/__init__.py
aiok/ad.py
aiok.egg-info/PKG-INFO
aiok.egg-info/SOURCES.txt
aiok.egg-info/dependency_links.txt
aiok.egg-info/requires.txt
aiok.egg-info/top_level.txt
aiok/bot/__init__.py
aiok/bot/api.py
aiok/bot/bot.py
aiok/bot/longpoll.py
aiok/dispatcher/__init__.py
aiok/dispatcher/dispatcher.py
aiok/dispatcher/executor.py
aiok/dispatcher/handler.py
aiok/dispatcher/storage.py
aiok/dispatcher/filters/__init__.py
aiok/dispatcher/filters/bildin.py
aiok/dispatcher/filters/factory.py
aiok/dispatcher/filters/filters.py
aiok/dispatcher/filters/state.py
aiok/types/__init__.py
aiok/types/action.py
aiok/types/attachment.py
aiok/types/base.py
aiok/types/fields.py
aiok/types/message.py
aiok/types/update.py
aiok/utils/__init__.py
aiok/utils/json.py
aiok/utils/mixins.py