Metadata-Version: 1.2
Name: aiok
Version: 0.3
Summary: async vkbot module
Home-page: https://github.com/14iq/aiok
Author: 14iq
Author-email: belicoff0505@gmail.com
License: MIT
Download-URL: https://github.com/14iq/aiok/archive/v_02.tar.gz
Keywords: SOME,MEANINGFULL,KEYWORDS
Platform: UNKNOWN
Classifier: Development Status :: 3 - Alpha
Classifier: Intended Audience :: Developers
Classifier: Topic :: Software Development :: Build Tools
Classifier: License :: OSI Approved :: MIT License
Classifier: Programming Language :: Python :: 3.8
Classifier: Programming Language :: Python :: 3.7
Requires-Python: >=3.7
